{
"EngyTime_4096_2_2":{
"name_dataset": "EngyTime",
"number_of_observations": 4096,
"dimension": 2 ,
"number_of_clusters": 2, 
"alpha_master":5.0,
"alpha_worker":5.0

},
"synthetic_5000_2_6":
{
"name_dataset":"synthetic",
"number_of_observations":5000,
"dimension":2,
"number_of_clusters":6,
"alpha_master":8.0,
"alpha_worker":8.0
},
"synthetic_20000_2_10":
{
"name_dataset":"synthetic",
"number_of_observations":20000,
"dimension":2,
"number_of_clusters":10,
"alpha_master":5.0,
"alpha_worker":5.0
},
"synthetic_10000_2_10":
{
"name_dataset":"synthetic",
"number_of_observations":10000,
"dimension":2,
"number_of_clusters":10,
"alpha_master":5.0,
"alpha_worker":5.0
},

"synthetic_40000_2_10":
{
"name_dataset":"synthetic",
"number_of_observations":40000,
"dimension":2,
"number_of_clusters":10,
"alpha_master":5.0,
"alpha_worker":5.0
},
"synthetic_60000_2_10":
{
"name_dataset":"synthetic",
"number_of_observations":60000,
"dimension":2,
"number_of_clusters":10,
"alpha_master":5.0,
"alpha_worker":5.0
},
"synthetic_80000_2_10":
{
"name_dataset":"synthetic",
"number_of_observations":80000,
"dimension":2,
"number_of_clusters":10,
"alpha_master":5.0,
"alpha_worker":5.0
},
"synthetic_100000_2_10":
{
"name_dataset":"synthetic",
"number_of_observations":100000,
"dimension":2,
"number_of_clusters":10,
"alpha_master":5.0,
"alpha_worker":5.0
},
"synthetic_1000000_2_10":
{
"name_dataset":"synthetic",
"number_of_observations":1000000,
"dimension":2,
"number_of_clusters":10,
"alpha_master":5.0,
"alpha_worker":5.0
},
"synthetic_10000_2_6":{
"name_dataset": "c_synthetic",
"number_of_clusters": 6, 
"dimension": 2 ,
"number_of_observations": 10000,
"alpha_master":5.0,
"alpha_worker":5.0
},

"balanced_131600_8_47":
{
"name_dataset":"balanced",
"number_of_observations":131600,
"dimension":8,
"number_of_clusters":47,
"alpha_master":1E-14,
"alpha_worker":1.0
},
"digits_280000_8_10":
{
"name_dataset":"digits",
"number_of_observations":280000,
"dimension":8,
"number_of_clusters":10,
"alpha_master":1E-14,
"alpha_worker":1.0
},
"emnist_letter_103600_8_26":
{
"name_dataset":"emnist_letter",
"number_of_observations":103600,
"dimension":8,
"number_of_clusters":26,
"alpha_master":1E-14,
"alpha_worker":1.0
},
"fashion-mnist_70000_8_10":
{
"name_dataset":"fashion-mnist",
"number_of_observations":70000,
"dimension":8,
"number_of_clusters":10,
"alpha_master":1E-14,
"alpha_worker":1.0
},
"mnist_70000_8_10":
{
"name_dataset":"mnist",
"number_of_observations":70000,
"dimension":8,
"number_of_clusters":10,
"alpha_master":1E-14,
"alpha_worker":1.0
},
"urbanGB_360177_2_469":
{
"name_dataset":"urbanGB",
"number_of_observations":360177,
"dimension":2,
"number_of_clusters":469,
"alpha_master":10.0,
"alpha_worker":10.0
}, 
}
